{
  "products": {
    "9848956198": {
      "id": 9848956198,
      "type": "مرتبة",
      "name": "ريترو",
      "category": "سوست متصلة",
      "weight": "",
      "thickness": "20",
      "width": "80",
      "height": "195",
      "price": "1506"
    },
    "1654987893516": {
      "id": 1654987893516,
      "type": "مرتبة",
      "name": "جولدن",
      "category": "سوست متصلة",
      "weight": "",
      "thickness": "26",
      "width": "90",
      "height": "195",
      "price": "2276"
    },
    "41869874862": {
      "id": 41869874862,
      "type": "مرتبة",
      "name": "دودو",
      "category": "سوست متصلة",
      "weight": "",
      "thickness": "30",
      "width": "90",
      "height": "195",
      "price": "3370"
    },
    "65148947561": {
      "id": 65148947561,
      "type": "مرتبة",
      "name": "سو",
      "category": "سوست منفصلة",
      "weight": "",
      "thickness": "25",
      "width": "90",
      "height": "195",
      "price": "3602"
    },
    "15648976513": {
      "id": 15648976513,
      "type": "مرتبة",
      "name": "ميموري",
      "category": "سوست متصلة",
      "weight": "",
      "thickness": "30",
      "width": "90",
      "height": "195",
      "price": "4576"
    },
    "165489643218": {
      "id": 165489643218,
      "type": "مرتبة",
      "name": "ماريو",
      "category": "طبية بدون سوست",
      "weight": "",
      "thickness": "15",
      "width": "90",
      "height": "195",
      "price": "2128"
    },
    "1654896168943218": {
      "id": 1654896168943218,
      "type": "مرتبة",
      "name": "ماريو",
      "category": "طبية بدون سوست",
      "weight": "",
      "thickness": "15",
      "width": "90",
      "height": "195",
      "price": "2128"
    },
    "1687489563165": {
      "id": 1687489563165,
      "type": "مخدة",
      "name": "",
      "thickness": "",
      "category": "",
      "weight": "625",
      "width": "40",
      "height": "60",
      "price": "99"
    },
    "1894894553289": {
      "id": 1894894553289,
      "type": "مخدة",
      "name": "ريلاكس",
      "thickness": "",
      "category": "",
      "weight": "",
      "width": "50",
      "height": "70",
      "price": "146"
    }
  },
  "warehouse": [{
      "product": "65148947561",
      "quantity": "3",
      "companyDiscount": "0.25"
    },
    {
      "product": "1894894553289",
      "quantity": "18",
      "companyDiscount": "0.3"
    },
    {
      "product": "1894894553289",
      "quantity": "18",
      "companyDiscount": "0.25"
    }
  ],
  "invocies": {
    "519848916": {
      "cutomerName": "Marwan Pablo",
      "shipmentAddress": "Palm hils villa 300",
      "invocieDate": 1639556836419,
      "receiptDate": 1639556836419,
      "order": [{
          "product": "65148947561",
          "quantity": "2",
          "price": "8500",
          "discount": "0.25"
        },
        {
          "product": "65148947561",
          "quantity": "3",
          "price": "250",
          "discount": "0.4"
        }
      ],
      "paymentMethod": "visa",
      "shipmentCharge": "200",
      "retailOffer": "",
      "totalPrice": "8750"
    }
  }
}